MANIFEST.in
README.md
setup.py
projit/__init__.py
projit/__main__.py
projit/ascii_plot.py
projit/cli.py
projit/config.py
projit/latex_table.py
projit/pdf.py
projit/projit.py
projit/template.py
projit/utils.py
projit.egg-info/PKG-INFO
projit.egg-info/SOURCES.txt
projit.egg-info/dependency_links.txt
projit.egg-info/entry_points.txt
projit.egg-info/requires.txt
projit.egg-info/top_level.txt
projit/templates/cookiecutter-data-science
projit/templates/default