Metadata-Version: 2.1
Name: projit
Version: 0.1.13
Summary: Python library and CLI for de-coupled data science project integration and management.
Home-page: http://john-hawkins.github.io
Author: John Hawkins
Author-email: john@getting-data-science-done.com
License: MIT
Project-URL: Documentation, https://projit.readthedocs.io
Project-URL: Source, https://github.com/john-hawkins/projit
Project-URL: Tracker, https://github.com/john-hawkins/projit/issues
